gen1/__init__.py
gen1/clip.py
gen1/midas.py
gen1/model.py
gen1-0.0.6.dist-info/LICENSE
gen1-0.0.6.dist-info/WHEEL
gen1-0.0.6.dist-info/METADATA
gen1-0.0.6.dist-info/RECORD
