Metadata-Version: 2.1
Name: gen1
Version: 0.0.6
Summary: Text to Video synthesis
Home-page: https://github.com/kyegomez/gen1
License: MIT
Keywords: Transformers,zeta scale
Author: Gen1
Author-email: kye@apac.ai
Requires-Python: >=3.8,<4.0
Classifier: License :: OSI Approved :: MIT License
Classifier: Programming Language :: Python :: 3
Classifier: Programming Language :: Python :: 3.8
Classifier: Programming Language :: Python :: 3.9
Classifier: Programming Language :: Python :: 3.10
Classifier: Programming Language :: Python :: 3.11
Classifier: Programming Language :: Python :: 3
Requires-Dist: einops
Requires-Dist: open_clip_torch
Requires-Dist: torch
Requires-Dist: transformers
Requires-Dist: zetascale
